CHANGELOG.txt
LICENCE.txt
MANIFEST.in
README.txt
setup.py
viscad/__init__.py
viscad/viscad.py
viscad.egg-info/PKG-INFO
viscad.egg-info/SOURCES.txt
viscad.egg-info/dependency_links.txt
viscad.egg-info/requires.txt
viscad.egg-info/top_level.txt