Metadata-Version: 2.1
Name: viscad
Version: 0.0.1.2
Summary: python vision functions for robotics
Home-page: https://robocadv.readthedocs.io/en/latest/docs/all_docs/viscad_docs/index.html
Author: Abdrakov Airat
Author-email: abdrakovairat@gmail.com
License: MIT
Keywords: function,vision,opencv
Platform: UNKNOWN
Classifier: Development Status :: 5 - Production/Stable
Classifier: Intended Audience :: Education
Classifier: Operating System :: Microsoft :: Windows :: Windows 10
Classifier: License :: OSI Approved :: MIT License
Classifier: Programming Language :: Python :: 3
License-File: LICENCE.txt
